status/__init__.py
status/_version.py
status/server.py
api_status-1.0.1.dist-info/METADATA
api_status-1.0.1.dist-info/WHEEL
api_status-1.0.1.dist-info/top_level.txt
api_status-1.0.1.dist-info/RECORD
