Metadata-Version: 2.1
Name: api-status
Version: 1.0.1
Summary: Simple way to make a /status for your services with python and asyncio.
Home-page: https://gitlab.com/pypa/sampleproject
Author: cdlr75
Author-email: cdlr75@gmail.com
License: UNKNOWN
Project-URL: Bug Reports, https://gitlab.com/cdlr75/status/issues
Project-URL: Source, https://gitlab.com/cdlr75/status/
Keywords: api status service
Platform: UNKNOWN
Classifier: Development Status :: 3 - Alpha
Classifier: Intended Audience :: Developers
Classifier: Topic :: Software Development :: Build Tools
Classifier: License :: OSI Approved :: MIT License
Classifier: Programming Language :: Python :: 3
Classifier: Programming Language :: Python :: 3.5
Classifier: Programming Language :: Python :: 3.6
Classifier: Programming Language :: Python :: 3.7
Requires-Python: >=3.6
Requires-Dist: aiohttp (>=3.5)
Provides-Extra: doc
Requires-Dist: sphinx ; extra == 'doc'
Requires-Dist: recommonmark ; extra == 'doc'
Requires-Dist: changelogfromtags ; extra == 'doc'
Provides-Extra: test
Requires-Dist: pytest ; extra == 'test'
Requires-Dist: pytest-cov ; extra == 'test'
Requires-Dist: asynctest ; extra == 'test'
Requires-Dist: pycodestyle ; extra == 'test'
Requires-Dist: pylint ; extra == 'test'
